fabrest/__init__.py
fabrest/client.py
fabrest/errors.py
fabrest/logger.py
fabrest/logging_catalog.py
fabrest/routes.py
fabrest/api/__init__.py
fabrest/api/auth.py
fabrest/api/client.py
fabrest/api/constant.py
fabrest/api/constants/__init__.py
fabrest/api/constants/collections.py
fabrest/api/constants/items.py
fabrest/api/constants/jobs.py
fabrest/api/constants/specialized.py
fabrest/api/constants/utils.py
fabrest/api/constants/workspace_collection.py
fabrest/api/constants/workspace_config.py
fabrest/models/__init__.py
fabrest/models/admin.py
fabrest/models/anomaly_detector.py
fabrest/models/apache_airflow_job.py
fabrest/models/copy_job.py
fabrest/models/cosmos_db_database.py
fabrest/models/data_pipeline.py
fabrest/models/dataflow.py
fabrest/models/digital_twin_builder.py
fabrest/models/digital_twin_builder_flow.py
fabrest/models/environment.py
fabrest/models/event_schema_set.py
fabrest/models/eventhouse.py
fabrest/models/eventstream.py
fabrest/models/graph_model.py
fabrest/models/graph_query_set.py
fabrest/models/graphql_api.py
fabrest/models/kql_dashboard.py
fabrest/models/kql_database.py
fabrest/models/kql_queryset.py
fabrest/models/lakehouse.py
fabrest/models/map.py
fabrest/models/mirrored_azure_databricks_catalog.py
fabrest/models/mirrored_database.py
fabrest/models/ml_experiment.py
fabrest/models/ml_model.py
fabrest/models/mounted_data_factory.py
fabrest/models/notebook.py
fabrest/models/ontology.py
fabrest/models/operations_agent.py
fabrest/models/paginated_report.py
fabrest/models/platform.py
fabrest/models/real_time_intelligence.py
fabrest/models/reflex.py
fabrest/models/report.py
fabrest/models/semantic_model.py
fabrest/models/snowflake_database.py
fabrest/models/spark.py
fabrest/models/spark_job_definition.py
fabrest/models/sql_database.py
fabrest/models/sql_endpoint.py
fabrest/models/user_data_function.py
fabrest/models/variable_library.py
fabrest/models/warehouse.py
fabrest/models/warehouse_snapshot.py
fabrest/resources/__init__.py
fabrest-1.0.0.dist-info/licenses/LICENSE
fabrest-1.0.0.dist-info/METADATA
fabrest-1.0.0.dist-info/WHEEL
fabrest-1.0.0.dist-info/top_level.txt
fabrest-1.0.0.dist-info/RECORD
