Metadata-Version: 2.4
Name: fabrest
Version: 1.0.0
Summary: A Python Fabric Rest Client to make requests to the Fabric API
Requires-Python: >=3.11
License-File: LICENSE
Requires-Dist: aiohttp>=3.12.11
Requires-Dist: azure-identity>=1.23.0
Requires-Dist: azure-storage-file-datalake>=12.20.0
Dynamic: license-file
